[
    {
        "id": 1,
        "title": "aaaa",
        "content": "aaaaaaaaaaaaaaaaaaaaaaaaaaaaa",
        "likes": 5,
        "creator": {
            "name": "Tarik Waleed",
            "isOnline": false,
            "followers": 10,
            "isFollowing": false
        }
    },
    {
        "id": 2,
        "title": "bbbb",
        "content": "bbbbbbbbbbbbbbbbbbbbbbbbbb",
        "likes": 5,
        "creator": {
            "name": "Ahmed Ali",
            "isOnline": true,
            "followers": 10,
            "isFollowing": true
        }
    },
    {
        "id": 3,
        "title": "ccc",
        "content": "ccccccccccccccccccccccccccccccccccccccccccccccccccccccc",
        "likes": 5,
        "creator": {
            "name": "Tarik Waleed",
            "isOnline": false,
            "followers": 10,
            "isFollowing": false
        }
    },
    {
        "id": 4,
        "title": "aaaa",
        "content": "aaaaaaaaaaaaaaaaaaaaaaaaaaaaa",
        "likes": 5,
        "creator": {
            "name": "Tarik Waleed",
            "isOnline": false,
            "followers": 10,
            "isFollowing": false
        }
    },
    {
        "id": 5,
        "title": "aaaa",
        "content": "aaaaaaaaaaaaaaaaaaaaaaaaaaaaa",
        "likes": 5,
        "creator": {
            "name": "Tarik Waleed",
            "isOnline": false,
            "followers": 10,
            "isFollowing": false
        }
    },
    {
        "id": 6,
        "title": "aaaa",
        "content": "aaaaaaaaaaaaaaaaaaaaaaaaaaaaa",
        "likes": 5,
        "creator": {
            "name": "Tarik Waleed",
            "isOnline": false,
            "followers": 10,
            "isFollowing": false
        }
    },
    {
        "id": 7,
        "title": "aaaa",
        "content": "aaaaaaaaaaaaaaaaaaaaaaaaaaaaa",
        "likes": 5,
        "creator": {
            "name": "Tarik Waleed",
            "isOnline": false,
            "followers": 10,
            "isFollowing": false
        }
    },
    {
        "id": 8,
        "title": "aaaa",
        "content": "aaaaaaaaaaaaaaaaaaaaaaaaaaaaa",
        "likes": 5,
        "creator": {
            "name": "Tarik Waleed",
            "isOnline": false,
            "followers": 10,
            "isFollowing": false
        }
    },
    {
        "id": 9,
        "title": "aaaa",
        "content": "aaaaaaaaaaaaaaaaaaaaaaaaaaaaa",
        "likes": 5,
        "creator": {
            "name": "Tarik Waleed",
            "isOnline": false,
            "followers": 10,
            "isFollowing": false
        }
    },
    {
        "id": 10,
        "title": "bbbb",
        "content": "bbbbbbbbbbbbbbbbbbbbbbbbbb",
        "likes": 5,
        "creator": {
            "name": "Ahmed Ali",
            "isOnline": true,
            "followers": 10,
            "isFollowing": true
        }
    },
    {
        "id": 11,
        "title": "ccc",
        "content": "ccccccccccccccccccccccccccccccccccccccccccccccccccccccc",
        "likes": 5,
        "creator": {
            "name": "Tarik Waleed",
            "isOnline": false,
            "followers": 10,
            "isFollowing": false
        }
    },
    {
        "id": 12,
        "title": "aaaa",
        "content": "aaaaaaaaaaaaaaaaaaaaaaaaaaaaa",
        "likes": 5,
        "creator": {
            "name": "Tarik Waleed",
            "isOnline": false,
            "followers": 10,
            "isFollowing": false
        }
    },
    {
        "id": 13,
        "title": "aaaa",
        "content": "aaaaaaaaaaaaaaaaaaaaaaaaaaaaa",
        "likes": 5,
        "creator": {
            "name": "Tarik Waleed",
            "isOnline": false,
            "followers": 10,
            "isFollowing": false
        }
    },
    {
        "id": 14,
        "title": "aaaa",
        "content": "aaaaaaaaaaaaaaaaaaaaaaaaaaaaa",
        "likes": 5,
        "creator": {
            "name": "Tarik Waleed",
            "isOnline": false,
            "followers": 10,
            "isFollowing": false
        }
    },
    {
        "id": 15,
        "title": "aaaa",
        "content": "aaaaaaaaaaaaaaaaaaaaaaaaaaaaa",
        "likes": 5,
        "creator": {
            "name": "Tarik Waleed",
            "isOnline": false,
            "followers": 10,
            "isFollowing": false
        }
    },
    {
        "id": 16,
        "title": "aaaa",
        "content": "aaaaaaaaaaaaaaaaaaaaaaaaaaaaa",
        "likes": 5,
        "creator": {
            "name": "Tarik Waleed",
            "isOnline": false,
            "followers": 10,
            "isFollowing": false
        }
    }
]